TEG/__init__.py
TEG/assets/__init__.py
TEG/envs/UR5_v0.py
TEG/envs/__init__.py
TEG/tools/__init__.py
TEG/tools/simulation.py
TEG-1.0.0rc1.dist-info/LICENSE
TEG-1.0.0rc1.dist-info/METADATA
TEG-1.0.0rc1.dist-info/WHEEL
TEG-1.0.0rc1.dist-info/top_level.txt
TEG-1.0.0rc1.dist-info/zip-safe
TEG-1.0.0rc1.dist-info/RECORD
