Metadata-Version: 2.1
Name: TEG
Version: 1.0.0rc1
Summary: Reinforcement Learning Environments for train RL agents
Author-email: Alexis Fraudita <fraumalex@gmail.com>
License: Apache License 2.0
Project-URL: Homepage, https://github.com/alefram/TEG
Project-URL: Bug Report, https://github.com/alefram/TEG/issues
Keywords: Reinforcement Learning,Mujoco,RL,AI,TEG
Classifier: Programming Language :: Python :: 3
Classifier: Programming Language :: Python :: 3.7
Classifier: Programming Language :: Python :: 3.8
Classifier: Programming Language :: Python :: 3.9
Classifier: Programming Language :: Python :: 3.10
Classifier: Programming Language :: Python :: 3.11
Classifier: License :: OSI Approved :: Apache Software License
Requires-Python: >=3.7
License-File: LICENSE
Requires-Dist: numpy >=1.23.5
Requires-Dist: mujoco >=2.3.1.post1
Requires-Dist: gymnasium >=0.27.1
Provides-Extra: testing
Requires-Dist: pytest ==7.1.3 ; extra == 'testing'
